hosty/__init__.py
hosty/hosty.py
hostypage-0.12.0.data/scripts/hostypage
hostypage-0.12.0.dist-info/METADATA
hostypage-0.12.0.dist-info/WHEEL
hostypage-0.12.0.dist-info/top_level.txt
hostypage-0.12.0.dist-info/RECORD
