Metadata-Version: 2.1
Name: hostypage
Version: 0.12.0
Summary: CLI for Hosty.Page
Home-page: UNKNOWN
Author: Hosty.Page
Author-email: christopherdavies553@gmail.com
License: UNKNOWN
Platform: UNKNOWN
Requires-Dist: click (==7.1.2)
Requires-Dist: requests (==2.25.1)
Requires-Dist: progress (==1.5)
